forgettable/__init__.py
forgettable/distribution.py
forgettable/server.py
forgettable-0.1.0.dist-info/DESCRIPTION.rst
forgettable-0.1.0.dist-info/entry_points.txt
forgettable-0.1.0.dist-info/METADATA
forgettable-0.1.0.dist-info/metadata.json
forgettable-0.1.0.dist-info/RECORD
forgettable-0.1.0.dist-info/top_level.txt
forgettable-0.1.0.dist-info/WHEEL
