Metadata-Version: 2.0
Name: forgettable
Version: 0.1.0
Summary: UNKNOWN
Home-page: https://github.com/bitly/forgettable/tree/master/pyforget
Author: Saul Shanabrook
Author-email: s.shanabrook@gmail.com
License: UNKNOWN
Platform: UNKNOWN
Requires-Dist: tornado
Requires-Dist: numpy
Requires-Dist: redis
